Epigrass/HelpEpg.html
Epigrass/Ui_about4.py
Epigrass/Ui_cpanel4new.py
Epigrass/Ui_display.py
Epigrass/Ui_epgeditor.py
Epigrass/Ui_neteditor.py
Epigrass/__init__.py
Epigrass/__init__.pyc
Epigrass/__version__.py
Epigrass/__version__.pyc
Epigrass/about.py
Epigrass/cpanel.py
Epigrass/dataObject.py
Epigrass/data_io.py
Epigrass/dgraph.py
Epigrass/display.ui
Epigrass/egicon.png
Epigrass/elasticnodes.py
Epigrass/epgeditor.py
Epigrass/epiRTplay.py
Epigrass/epigdal.py
Epigrass/epigrass.py
Epigrass/epigrass.qrc
Epigrass/epigrass_es.qm
Epigrass/epigrass_es.ts
Epigrass/epigrass_fr.qm
Epigrass/epigrass_fr.ts
Epigrass/epigrass_rc.py
Epigrass/epigrass_ru_RU.qm
Epigrass/epigrass_ru_RU.ts
Epigrass/epimodels.py
Epigrass/epiplay.py
Epigrass/manager.py
Epigrass/manager_pt_BR.qm
Epigrass/manager_pt_BR.ts
Epigrass/neteditor.py
Epigrass/neteditor.ui
Epigrass/primitives.py
Epigrass/pylabQtcanvas.py
Epigrass/qtgraph.py
Epigrass/report.py
Epigrass/rinterface.py
Epigrass/simobj.py
Epigrass/spread.py
epigrass-2.4.6.dist-info/DESCRIPTION.rst
epigrass-2.4.6.dist-info/METADATA
epigrass-2.4.6.dist-info/RECORD
epigrass-2.4.6.dist-info/WHEEL
epigrass-2.4.6.dist-info/entry_points.txt
epigrass-2.4.6.dist-info/metadata.json
epigrass-2.4.6.dist-info/top_level.txt
