Metadata-Version: 2.0
Name: epigrass
Version: 2.4.6
Summary: Epidemiological Geo-Referenced Analysis and Simulation System
Home-page: http://epigrass.sourceforge.net
Author: Flavio Codeco Coelho
Author-email: fccoelho@gmail.com
License: GPL
Download-URL: http://sourceforge.net/project/showfiles.php?group_id=128000
Platform: UNKNOWN
Requires-Dist: SQLAlchemy (>=0.7)
Requires-Dist: networkx (>=1.1)
Requires-Dist: numpy (>=1.2)
Requires-Dist: redis (>=2.4)
Requires-Dist: requests
Requires-Dist: sqlsoup
